alphapose/__init__.py
alphapose/opt.py
alphapose/version.py
alphapose/datasets/__init__.py
alphapose/datasets/coco_det.py
alphapose/datasets/coco_wholebody.py
alphapose/datasets/coco_wholebody_det.py
alphapose/datasets/concat_dataset.py
alphapose/datasets/custom.py
alphapose/datasets/halpe_136.py
alphapose/datasets/halpe_136_det.py
alphapose/datasets/halpe_26.py
alphapose/datasets/halpe_26_det.py
alphapose/datasets/mpii.py
alphapose/datasets/mscoco.py
alphapose/models/__init__.py
alphapose/models/builder.py
alphapose/models/criterion.py
alphapose/models/fastpose.py
alphapose/models/fastpose_duc.py
alphapose/models/fastpose_duc_dense.py
alphapose/models/hardnet.py
alphapose/models/hrnet.py
alphapose/models/simplepose.py
alphapose/utils/__init__.py
alphapose/utils/bbox.py
alphapose/utils/config.py
alphapose/utils/detector.py
alphapose/utils/env.py
alphapose/utils/file_detector.py
alphapose/utils/logger.py
alphapose/utils/metrics.py
alphapose/utils/pPose_nms.py
alphapose/utils/registry.py
alphapose/utils/transforms.py
alphapose/utils/vis.py
alphapose/utils/webcam_detector.py
alphapose/utils/writer.py
alphapose/utils/presets/__init__.py
alphapose/utils/presets/simple_transform.py
alphapose/utils/roi_align/__init__.py
alphapose/utils/roi_align/roi_align.py
trackers/__init__.py
trackers/tracker_api.py
trackers/tracker_cfg.py
trackers/ReidModels/ResBnLin.py
trackers/ReidModels/ResNet.py
trackers/ReidModels/__init__.py
trackers/ReidModels/bn_linear.py
trackers/ReidModels/net_utils.py
trackers/ReidModels/osnet.py
trackers/ReidModels/osnet_ain.py
trackers/ReidModels/resnet_fc.py
trackers/ReidModels/backbone/__init__.py
trackers/ReidModels/backbone/googlenet.py
trackers/ReidModels/backbone/lrn.py
trackers/ReidModels/backbone/sqeezenet.py
trackers/ReidModels/classification/__init__.py
trackers/ReidModels/classification/classifier.py
trackers/ReidModels/classification/rfcn_cls.py
trackers/ReidModels/psroi_pooling/__init__.py
trackers/ReidModels/psroi_pooling/build.py
alphapose-1.1.dist-info/LICENSE
alphapose-1.1.dist-info/METADATA
alphapose-1.1.dist-info/WHEEL
alphapose-1.1.dist-info/top_level.txt
alphapose-1.1.dist-info/RECORD
